setup.py
./__init__.py
./restruct.py
restruct.egg-info/PKG-INFO
restruct.egg-info/SOURCES.txt
restruct.egg-info/dependency_links.txt
restruct.egg-info/requires.txt
restruct.egg-info/top_level.txt