Metadata-Version: 1.1
Name: restruct
Version: 0.2.0
Summary: Turn SQL results into beautiful JSON structures
Home-page: https://github.com/webheroesinc/restruct
Author: Matthew Brisebois
Author-email: matthew@webheroes.ca
License: Dual License; GPLv3 and Proprietary
Keywords: mysql,sqlite,sql,json
Platform: UNKNOWN
Classifier: License :: OSI Approved :: GNU General Public License v3 or later (GPLv3+)
Classifier: License :: Other/Proprietary License
Classifier: Programming Language :: Python :: 3.5
Classifier: Development Status :: 4 - Beta
Classifier: Intended Audience :: Developers
